hello3/__init__.py
hello3/hello.py
hello3-0.1.0.dist-info/METADATA
hello3-0.1.0.dist-info/WHEEL
hello3-0.1.0.dist-info/top_level.txt
hello3-0.1.0.dist-info/RECORD
