Metadata-Version: 2.1
Name: hello3
Version: 0.1.0
Summary: A simple hello world library
Home-page: https://github.com/qq1060656096/dev/py/hello
Author: zwei
Author-email: 1060656096@qq.com
Classifier: Programming Language :: Python :: 3
Classifier: License :: OSI Approved :: MIT License
Classifier: Operating System :: OS Independent
Requires-Python: >=3.6
